inoopa_utils/__init__.py
inoopa_utils/address_parser.py
inoopa_utils/common_mongo_filters.py
inoopa_utils/dns_helpers.py
inoopa_utils/helpers.py
inoopa_utils/inoopa_logging.py
inoopa_utils/mongodb_helpers.py
inoopa_utils/openai_helpers.py
inoopa_utils/rabbitmq_helpers.py
inoopa_utils/typesense_helpers.py
inoopa_utils/custom_types/__init__.py
inoopa_utils/custom_types/addresses.py
inoopa_utils/custom_types/companies.py
inoopa_utils/custom_types/db_stats.py
inoopa_utils/custom_types/decision_makers.py
inoopa_utils/custom_types/delivery_filters.py
inoopa_utils/custom_types/delivery_memory.py
inoopa_utils/custom_types/exceptions.py
inoopa_utils/custom_types/keywords.py
inoopa_utils/custom_types/legal_filters.py
inoopa_utils/custom_types/openai.py
inoopa_utils/custom_types/phone_operators.py
inoopa_utils/custom_types/typesense_schemas.py
inoopa_utils/custom_types/website_structure.py
inoopa_utils/utils/__init__.py
inoopa_utils/utils/env_variables_helper.py
inoopa_utils/utils/exceptions.py
inoopa_utils-10.5.0.dist-info/METADATA
inoopa_utils-10.5.0.dist-info/WHEEL
inoopa_utils-10.5.0.dist-info/RECORD
