Metadata-Version: 2.4
Name: inoopa_utils
Version: 10.5.0
Summary: Collection of utils used at Inoopa.
Project-URL: Repository, https://bitbucket.org/inoopa/inoopa_utils/
Author-email: Maxim Berge <maxim.berge@inoopa.com>
Requires-Python: >=3.10
Requires-Dist: aiodns>=3.2.0
Requires-Dist: anthropic>=0.59.0
Requires-Dist: boto3>=1.40.69
Requires-Dist: logfire>=4.3.3
Requires-Dist: openai>=1.14.3
Requires-Dist: pandas>=2.3.3
Requires-Dist: pendulum>=2.1.2
Requires-Dist: pydantic==2.11.7
Requires-Dist: pymongo>=4.15.3
Requires-Dist: python-dotenv==1.2.1
Requires-Dist: rabbitpy>=2.0.1
Requires-Dist: requests>=2.32.5
Requires-Dist: rich>=14.2.0
Requires-Dist: tenacity>=8.2.3
Requires-Dist: tiktoken>=0.12.0
Requires-Dist: tldextract>=5.1.2
Requires-Dist: typesense>=0.21.0
Requires-Dist: unidecode>=1.3.8
